[
    {
        "transactionName": "open_main_page",
        "rawStartTime": 1616863167051,
        "rawEndTime": 1616863167428
    },
    {
        "transactionName": "login",
        "rawStartTime": 1616863167430,
        "rawEndTime": 1616863167740
    },
    {
        "transactionName": "open_flights_page",
        "rawStartTime": 1616863167743,
        "rawEndTime": 1616863168475
    },
    {
        "transactionName": "search_flights",
        "rawStartTime": 1616863168477,
        "rawEndTime": 1616863168618
    },
    {
        "transactionName": "logout",
        "rawStartTime": 1616863168620,
        "rawEndTime": 1616863168805
    },
    {
        "transactionName": "UC_03_SearchFlights",
        "rawStartTime": 1616863167049,
        "rawEndTime": 1616863168807
    }
]